{"name":"Xtd","tagline":"","body":"# XTD  \r\nThis is a driver for the XTD utilizing the Raspberry Pi.  \r\n\r\n# Installation and Usage  \r\nDownload the code from the [respository](https://github.com/rshin808/XTD).  \r\nGo to the mainDriver directory. The directory tree is shown below:  \r\n```\r\nXTD/\r\n    examples/\r\n    mainDriver/\r\n```  \r\nmainDriver contains the current working code for a default and interactive driver.  \r\nIn order to run the default driver  use the command:  \r\n```\r\npython defaultDriver.py\r\n```\r\n\r\nIn order to run the interactive driver use the command:  \r\n```\r\npython driver.py\r\n```\r\n\r\nTo set the defaultDriver.py to run on startup, edit the \"/etc/rc.local\" file.  \r\nAdd this line:  \r\n```\r\npython /path-to-XTD/XTD/mainDriver/defaultDriver.py &\r\n```  \r\n","google":"","note":"Don't delete this file! It's used internally to help with page regeneration."}